geosptools/__init__.py
geosptools/raster_tools.py
geosptools-3.3.9.dist-info/licenses/LICENSE
geosptools-3.3.9.dist-info/METADATA
geosptools-3.3.9.dist-info/WHEEL
geosptools-3.3.9.dist-info/top_level.txt
geosptools-3.3.9.dist-info/RECORD
